<?xml version="1.0"?>
<arts format="ascii" version="1">
<GriddedField3 name="">
<Vector name="Pressure" nelem="137">
101204.94
100953.63
100679.0
100379.06
100051.65
99694.52
99305.26999999999
98881.33
98420.02
97918.52
97373.92
96783.15
96143.11
95450.59
94702.4
93895.32
93026.18
92091.93000000001
91089.65
90016.69
88870.66
87649.57
86351.9
84976.68
83523.58
81993.02
80386.22
78705.28
76953.29000000001
75134.26
73253.25
71316.31
69330.43000000001
67303.52
65244.240000000005
63161.94
61066.45999999999
58967.97
56876.78
54803.12
52756.96000000001
50750.21
48794.7
46897.08
45058.58
43277.92
41553.87
39885.16
38270.58
36708.89
35198.87
33739.32
32329.039999999997
30966.840000000004
29651.549999999996
28382.0
27157.04
25975.53
24836.34
23738.37
22680.5
21661.66
20680.78
19736.79
18828.67
17955.37
17115.91
16309.27
15534.48
14790.58
14076.630000000001
13391.7
12734.869999999999
12105.26
11501.98
10924.17
10371.0
9841.64
9335.27
8851.12
8388.16
7944.96
7519.99
7111.870000000001
6719.410000000001
6341.51
5977.21
5625.67
5286.4400000000005
4959.5199999999995
4644.9800000000005
4342.87
4053.21
3775.98
3511.11
3258.43
3017.76
2788.87
2571.56
2365.6
2170.7599999999998
1986.81
1813.4799999999998
1650.5400000000002
1497.7
1354.69
1221.23
1097.03
981.77
875.16
776.86
686.54
603.88
528.51
460.1
398.28999999999996
342.7
292.98
248.74999999999997
209.64999999999998
175.31
145.35
119.41999999999999
97.16
78.21000000000001
62.239999999999995
48.92
37.93
28.99
21.8
16.11
11.68
8.290000000000001
5.75
3.88
2.55
1.0
</Vector>
<Vector name="Latitude" nelem="1">
0.0000000e+00
</Vector>
<Vector name="Longitude" nelem="1">
0.0000000e+00
</Vector>
<Tensor3 name="Data" npages="137" nrows="1" ncols="1">
5.3006932e-08
5.3403006e-08
5.3740003e-08
5.40247e-08
5.4263246e-08
5.4461175e-08
5.4623438e-08
5.47545e-08
5.485825e-08
5.493816e-08
5.499724e-08
5.5038125e-08
5.506303e-08
5.5073876e-08
5.5072263e-08
5.5067208e-08
5.5051252e-08
5.5027904e-08
5.4991286e-08
5.49442e-08
5.4889316e-08
5.4828593e-08
5.4761312e-08
5.468792e-08
5.4608773e-08
5.4523422e-08
5.443312e-08
5.4344103e-08
5.426389e-08
5.419975e-08
5.4155127e-08
5.4132567e-08
5.413822e-08
5.418332e-08
5.4282037e-08
5.4451768e-08
5.471144e-08
5.506789e-08
5.551338e-08
5.603236e-08
5.659135e-08
5.7126606e-08
5.756808e-08
5.788681e-08
5.8143836e-08
5.8541218e-08
5.9520982e-08
6.1667556e-08
6.57182e-08
7.259799e-08
8.3214296e-08
9.834258e-08
1.1848618e-07
1.4385138e-07
1.7428648e-07
2.0931829e-07
2.4837644e-07
2.9071765e-07
3.3545942e-07
3.816965e-07
4.2830342e-07
4.74238e-07
5.187194e-07
5.611818e-07
6.011618e-07
6.387618e-07
6.746803e-07
7.100235e-07
7.460488e-07
7.841828e-07
8.258275e-07
8.72461e-07
9.254171e-07
9.859024e-07
1.05533e-06
1.134939e-06
1.2255725e-06
1.3281124e-06
1.4431031e-06
1.5700537e-06
1.7080287e-06
1.8560041e-06
2.012843e-06
2.1773062e-06
2.348023e-06
2.5230515e-06
2.6999296e-06
2.876179e-06
3.0495885e-06
3.2182993e-06
3.3806068e-06
3.534735e-06
3.6797317e-06
3.816231e-06
3.945695e-06
4.0690934e-06
4.1867493e-06
4.299894e-06
4.4105477e-06
4.5217666e-06
4.638244e-06
4.7644744e-06
4.902108e-06
5.053889e-06
5.221274e-06
5.4043057e-06
5.6028907e-06
5.810387e-06
6.0164543e-06
6.2072036e-06
6.365975e-06
6.4754386e-06
6.5188674e-06
6.488665e-06
6.379595e-06
6.188758e-06
5.9221725e-06
5.590562e-06
5.2052605e-06
4.7766166e-06
4.311612e-06
3.83027e-06
3.1166458e-06
2.6797477e-06
2.2848267e-06
1.9422014e-06
1.659115e-06
1.4390962e-06
1.2813179e-06
1.1799576e-06
1.1235583e-06
1.0943874e-06
1.067796e-06
1.0115807e-06
8.853421e-07
6.398447e-07
2.1637811e-07
</Tensor3>
</GriddedField3>
</arts>
